LICENSE
sixi_web/__init__.py
sixi_web/api.py
sixi_web/middleware.py
sixi_web/orm.py
sixi_web/response.py
sixi_web-0.1.4.dist-info/LICENSE
sixi_web-0.1.4.dist-info/WHEEL
sixi_web-0.1.4.dist-info/METADATA
sixi_web-0.1.4.dist-info/RECORD
