Metadata-Version: 2.1
Name: sixi-web
Version: 0.1.4
Summary: A simple web framework built for learning purpose.
Home-page: https://github.com/kadaliao/sixi-web
License: MIT
Keywords: web,learning
Author: Kada Liao
Author-email: kadaliao@gmail.com
Requires-Python: >=3.9,<4.0
Classifier: License :: OSI Approved :: MIT License
Classifier: Programming Language :: Python :: 3
Requires-Dist: Jinja2 (>=3.0.1,<4.0.0)
Requires-Dist: WebOb (>=1.8.7,<2.0.0)
Requires-Dist: parse (>=1.19.0,<2.0.0)
Requires-Dist: requests (>=2.26.0,<3.0.0)
Requires-Dist: requests-wsgi-adapter (>=0.4.1,<0.5.0)
Requires-Dist: whitenoise (>=5.3.0,<6.0.0)
Project-URL: Repository, https://github.com/kadaliao/sixi-web
